CHANGELOG.md
neptune_mlflow_exporter/__init__.py
neptune_mlflow_exporter/impl/__init__.py
neptune_mlflow_exporter/impl/artifact_strategy.py
neptune_mlflow_exporter/impl/components/__init__.py
neptune_mlflow_exporter/impl/components/config.py
neptune_mlflow_exporter/impl/components/exporter.py
neptune_mlflow_exporter/impl/components/fetcher.py
neptune_mlflow_exporter/impl/neptune_exporter.py
neptune_mlflow_exporter/impl/orchestrator.py
neptune_mlflow_exporter/impl/sync.py
neptune_mlflow_exporter/impl/version.py
neptune_mlflow_plugin/__init__.py
neptune_mlflow_plugin/impl/__init__.py
neptune_mlflow_plugin/impl/plugin.py
neptune_mlflow_plugin/impl/utils.py
neptune_mlflow-1.1.1.dist-info/LICENSE
neptune_mlflow-1.1.1.dist-info/METADATA
neptune_mlflow-1.1.1.dist-info/WHEEL
neptune_mlflow-1.1.1.dist-info/entry_points.txt
neptune_mlflow-1.1.1.dist-info/RECORD
